pyironscales/__init__.py
pyironscales/config.py
pyironscales/exceptions.py
pyironscales/interfaces.py
pyironscales/py.typed
pyironscales/types.py
pyironscales/clients/__init__.py
pyironscales/clients/base_client.py
pyironscales/clients/ironscales_client.py
pyironscales/endpoints/__init__.py
pyironscales/endpoints/base/__init__.py
pyironscales/endpoints/base/base_endpoint.py
pyironscales/endpoints/ironscales/CampaignsEndpoint.py
pyironscales/endpoints/ironscales/CampaignsIdDetailsEndpoint.py
pyironscales/endpoints/ironscales/CampaignsIdEndpoint.py
pyironscales/endpoints/ironscales/CampaignsIdParticipantDetailsEndpoint.py
pyironscales/endpoints/ironscales/CompanyCreateEndpoint.py
pyironscales/endpoints/ironscales/CompanyEndpoint.py
pyironscales/endpoints/ironscales/CompanyId911EmailEndpoint.py
pyironscales/endpoints/ironscales/CompanyIdAutoSyncEndpoint.py
pyironscales/endpoints/ironscales/CompanyIdAutoSyncGroupsEndpoint.py
pyironscales/endpoints/ironscales/CompanyIdAutoSyncMailboxesEndpoint.py
pyironscales/endpoints/ironscales/CompanyIdEndpoint.py
pyironscales/endpoints/ironscales/CompanyIdFeaturesEndpoint.py
pyironscales/endpoints/ironscales/CompanyIdManifestEndpoint.py
pyironscales/endpoints/ironscales/CompanyIdStatsEndpoint.py
pyironscales/endpoints/ironscales/CompanyListEndpoint.py
pyironscales/endpoints/ironscales/CompanyListV2Endpoint.py
pyironscales/endpoints/ironscales/EmailsEndpoint.py
pyironscales/endpoints/ironscales/EmailsIdEndpoint.py
pyironscales/endpoints/ironscales/IncidentEndpoint.py
pyironscales/endpoints/ironscales/IncidentIdClassifyEndpoint.py
pyironscales/endpoints/ironscales/IncidentIdClassifyIdEndpoint.py
pyironscales/endpoints/ironscales/IncidentIdDetailsEndpoint.py
pyironscales/endpoints/ironscales/IncidentIdDetailsIdEndpoint.py
pyironscales/endpoints/ironscales/IncidentIdEndpoint.py
pyironscales/endpoints/ironscales/IncidentIdListEndpoint.py
pyironscales/endpoints/ironscales/IncidentIdScanbackListEndpoint.py
pyironscales-0.1.5.dist-info/METADATA
pyironscales-0.1.5.dist-info/WHEEL
pyironscales-0.1.5.dist-info/licenses/LICENSE
pyironscales-0.1.5.dist-info/RECORD
