Metadata-Version: 2.4
Name: pyironscales
Version: 0.1.5
Summary: A full-featured Python client for the Ironscales API
Project-URL: Homepage, https://github.com/brygphilomena/pyironscales
Project-URL: Issues, https://github.com/brygphilomena/pyironscales/issues
Author-email: Peter Annabel <peter.annabel@gmail.com>
License-Expression: GPL-3.0-only
License-File: LICENSE
Keywords: API,Annotated,Client,Ironscales,MSP,Python,Typed
Classifier: Intended Audience :: Developers
Classifier: License :: OSI Approved :: GNU General Public License v3 or later (GPLv3+)
Classifier: Programming Language :: Python :: 3.10
Classifier: Programming Language :: Python :: 3.11
Classifier: Topic :: Software Development :: Libraries :: Python Modules
Requires-Python: >=3.9
Requires-Dist: pydantic
Requires-Dist: requests
Requires-Dist: typing-extensions
